beratools/__init__.py
beratools/core/__init__.py
beratools/core/algo_centerline.py
beratools/core/algo_common.py
beratools/core/algo_cost.py
beratools/core/algo_dijkstra.py
beratools/core/algo_footprint_rel.py
beratools/core/algo_line_grouping.py
beratools/core/algo_merge_lines.py
beratools/core/algo_split_with_lines.py
beratools/core/algo_tiler.py
beratools/core/algo_vertex_optimization.py
beratools/core/constants.py
beratools/core/logger.py
beratools/core/tool_base.py
beratools/gui/__init__.py
beratools/gui/batch_processing_dlg.py
beratools/gui/bt_data.py
beratools/gui/bt_gui_main.py
beratools/gui/main.py
beratools/gui/map_window.py
beratools/gui/tool_widgets.py
beratools/gui/assets/BERALogo.png
beratools/gui/assets/beratools.json
beratools/gui/assets/closed.gif
beratools/gui/assets/closed.png
beratools/gui/assets/gui.json
beratools/gui/assets/open.gif
beratools/gui/assets/open.png
beratools/gui/assets/tool.gif
beratools/gui/assets/tool.png
beratools/tools/Beratools_r_script.r
beratools/tools/Ht_metrics.py
beratools/tools/__init__.py
beratools/tools/batch_processing.py
beratools/tools/canopy_threshold_relative.py
beratools/tools/canopycostraster.py
beratools/tools/centerline.py
beratools/tools/common.py
beratools/tools/fl_regen_csf.py
beratools/tools/forest_line_attributes.py
beratools/tools/line_footprint_absolute.py
beratools/tools/line_footprint_fixed.py
beratools/tools/line_footprint_functions.py
beratools/tools/line_footprint_relative.py
beratools/tools/line_grouping.py
beratools/tools/ln_relative_metrics.py
beratools/tools/r_cal_lpi_elai.r
beratools/tools/r_generate_pd_focalraster.r
beratools/tools/r_interface.py
beratools/tools/r_point_density.r
beratools/tools/rpy_chm2trees.py
beratools/tools/rpy_dsm_chm_by.py
beratools/tools/rpy_dtm_by.py
beratools/tools/rpy_find_cellsize.py
beratools/tools/rpy_gnd_csf.py
beratools/tools/rpy_hummock_hollow.py
beratools/tools/rpy_hummock_hollow_raster.py
beratools/tools/rpy_las_info.py
beratools/tools/rpy_laz2las.py
beratools-0.2.3.dist-info/METADATA
beratools-0.2.3.dist-info/WHEEL
beratools-0.2.3.dist-info/entry_points.txt
beratools-0.2.3.dist-info/licenses/LICENSE
beratools-0.2.3.dist-info/RECORD
