Metadata-Version: 2.4
Name: BERATools
Version: 0.2.3
Summary: An advanced forest line feature analysis platform
Project-URL: Homepage, https://github.com/RichardQZeng/BTools
Author-email: AppliedGRG <appliedgrg@gmail.com>, Richard Zeng <richardqzeng@gmail.com>
License: MIT License
License-File: LICENSE
Keywords: BERA,Line
Classifier: Development Status :: 2 - Pre-Alpha
Classifier: Intended Audience :: Developers
Classifier: License :: OSI Approved :: MIT License
Classifier: Natural Language :: English
Classifier: Programming Language :: Python :: 3
Classifier: Programming Language :: Python :: 3.10
Classifier: Programming Language :: Python :: 3.11
Classifier: Programming Language :: Python :: 3.12
Requires-Python: >=3.10
Requires-Dist: bera-centerlines
Requires-Dist: gdal>=3.9.2
Requires-Dist: geopandas
Requires-Dist: pip
Requires-Dist: psutil
Requires-Dist: pyogrio>=0.9.0
Requires-Dist: pyqt5
Requires-Dist: pyqtlet2
Requires-Dist: pytest
Requires-Dist: pyyaml
Requires-Dist: rioxarray
Requires-Dist: scikit-image>=0.24.0
Requires-Dist: tqdm
Requires-Dist: xarray-spatial
